{
  "config" : {
    "max_traffics" : "23384800",
    "max_app" : "100000000",
    "max_twitter" : "44400",
    "max_instagram" : "873320",
    "max_facebook" : "27220100",
    "max_employees" : "481"
  },
  "data" :[
  {
    "key": 0,
    "name": "Lazada",
    "url": "http://www.lazada.com.my/",
    "logodesktop": "logo/my/desktop/lazada.png",
    "traffics": 23384800,
    "ios": 2,
    "android": 2,
    "twitter": 32450,
    "instagram": 467670,
    "facebook": 27220100,
    "employees": 481,
    "type": "b2c",
    "category": "general",
    "location": "international",
    "verified": "",
    "iema_winner": "TRUE"
  },
  {
    "key": 1,
    "name": "Shopee",
    "url": "https://shopee.com.my",
    "logodesktop": "logo/my/desktop/shopee.png",
    "traffics": 15790900,
    "ios": 1,
    "android": 1,
    "twitter": 110,
    "instagram": 362180,
    "facebook": 13246900,
    "employees": 271,
    "type": "c2c",
    "category": "general",
    "location": "international",
    "verified": "",
    "iema_winner": ""
  },
  {
    "key": 2,
    "name": "11 Street",
    "url": "http://www.11street.my/",
    "logodesktop": "logo/my/desktop/11street.png",
    "traffics": 7829000,
    "ios": 5,
    "android": 6,
    "twitter": 44400,
    "instagram": 123130,
    "facebook": 1648200,
    "employees": 169,
    "type": "b2c",
    "category": "general",
    "location": "international",
    "verified": "",
    "iema_winner": ""
  },
  {
    "key": 3,
    "name": "Lelong",
    "url": "https://www.lelong.com.my/",
    "logodesktop": "logo/my/desktop/lelong.png",
    "traffics": 5104900,
    "ios": 10,
    "android": 8,
    "twitter": 780,
    "instagram": 8680,
    "facebook": 415400,
    "employees": 69,
    "type": "c2c",
    "category": "general",
    "location": "malaysia",
    "verified": "",
    "iema_winner": ""
  },
  {
    "key": 4,
    "name": "Zalora",
    "url": "https://www.zalora.com.my",
    "logodesktop": "logo/my/desktop/zalora.png",
    "traffics": 1520300,
    "ios": 3,
    "android": 4,
    "twitter": 27280,
    "instagram": 335620,
    "facebook": 7647200,
    "employees": 241,
    "type": "b2c",
    "category": "fashion",
    "location": "international",
    "verified": "",
    "iema_winner": ""
  },
  {
    "key": 5,
    "name": "eBay",
    "url": "https://www.ebay.com.my/",
    "logodesktop": "logo/my/desktop/ebay.png",
    "traffics": 1003800,
    "ios": 9,
    "android": 9,
    "twitter": 160,
    "instagram": 230,
    "facebook": 431100,
    "employees": 53,
    "type": "c2c",
    "category": "general",
    "location": "international",
    "verified": "",
    "iema_winner": ""
  },
  {
    "key": 6,
    "name": "Qoo10",
    "url": "https://www.qoo10.my",
    "logodesktop": "logo/my/desktop/qoo10.png",
    "traffics": 844900,
    "ios": 13,
    "android": 12,
    "twitter": 200,
    "instagram": 0,
    "facebook": 282100,
    "employees": 8,
    "type": "b2c",
    "category": "general",
    "location": "international",
    "verified": "",
    "iema_winner": ""
  },
  {
    "key": 7,
    "name": "GoShop",
    "url": "http://www.goshop.com.my/index.do",
    "logodesktop": "logo/my/desktop/goshop.png",
    "traffics": 836900,
    "ios": 7,
    "android": 3,
    "twitter": 12930,
    "instagram": 111110,
    "facebook": 543200,
    "employees": 19,
    "type": "b2c",
    "category": "general",
    "location": "malaysia",
    "verified": "",
    "iema_winner": ""
  },
  {
    "key": 8,
    "name": "Hermo",
    "url": "https://www.hermo.my/",
    "logodesktop": "logo/my/desktop/hermo.png",
    "traffics": 699900,
    "ios": 8,
    "android": 11,
    "twitter": 130,
    "instagram": 153180,
    "facebook": 265800,
    "employees": 41,
    "type": "b2c",
    "category": "fashion",
    "location": "malaysia",
    "verified": "",
    "iema_winner": ""
  },
  {
    "key": 9,
    "name": "ezbuy",
    "url": "https://ezbuy.my/",
    "logodesktop": "logo/my/desktop/ezbuy.png",
    "traffics": 542100,
    "ios": 6,
    "android": 7,
    "twitter": 0,
    "instagram": 68290,
    "facebook": 768200,
    "employees": 25,
    "type": "b2c",
    "category": "general",
    "location": "international",
    "verified": "",
    "iema_winner": ""
  },
  {
    "key": 10,
    "name": "Fashion Valet",
    "url": "https://www.fashionvalet.com/",
    "logodesktop": "logo/my/desktop/fashionvalet.png",
    "traffics": 352100,
    "ios": 99,
    "android": 99,
    "twitter": 12080,
    "instagram": 575730,
    "facebook": 261300,
    "employees": 86,
    "type": "b2c",
    "category": "fashion",
    "location": "malaysia",
    "verified": "",
    "iema_winner": ""
  },
  {
    "key": 11,
    "name": "uBuy",
    "url": "https://www.ubuy.com.my/en/",
    "logodesktop": "logo/my/desktop/ubuy.png",
    "traffics": 347000,
    "ios": 99,
    "android": 99,
    "twitter": 0,
    "instagram": 87800,
    "facebook": 300,
    "employees": 0,
    "type": "b2c",
    "category": "general",
    "location": "international",
    "verified": "",
    "iema_winner": ""
  },
  {
    "key": 12,
    "name": "Sephora",
    "url": "https://www.sephora.my/",
    "logodesktop": "logo/my/desktop/sephora.png",
    "traffics": 342000,
    "ios": 4,
    "android": 10,
    "twitter": 7170,
    "instagram": 294430,
    "facebook": 18118700,
    "employees": 87,
    "type": "b2c",
    "category": "fashion",
    "location": "international",
    "verified": "",
    "iema_winner": ""
  },
  {
    "key": 13,
    "name": "CJ WOW SHOP",
    "url": "http://www.cjwowshop.com.my/",
    "logodesktop": "logo/my/desktop/wowshop.png",
    "traffics": 338700,
    "ios": 11,
    "android": 5,
    "twitter": 740,
    "instagram": 33830,
    "facebook": 65200,
    "employees": 34,
    "type": "b2c",
    "category": "general",
    "location": "malaysia",
    "verified": "",
    "iema_winner": ""
  },
  {
    "key": 14,
    "name": "SG Shop",
    "url": "https://www.sgshop.com.my/",
    "logodesktop": "logo/my/desktop/sgshop.png",
    "traffics": 222500,
    "ios": 15,
    "android": 16,
    "twitter": 0,
    "instagram": 4600,
    "facebook": 85000,
    "employees": 8,
    "type": "b2c",
    "category": "general",
    "location": "international",
    "verified": "",
    "iema_winner": ""
  },
  {
    "key": 15,
    "name": "Photobook",
    "url": "http://www.photobook.com.my/",
    "logodesktop": "logo/my/desktop/photobook.png",
    "traffics": 205400,
    "ios": 99,
    "android": 99,
    "twitter": 4860,
    "instagram": 0,
    "facebook": 381200,
    "employees": 122,
    "type": "b2c",
    "category": "general",
    "location": "international",
    "verified": "",
    "iema_winner": ""
  },
  {
    "key": 16,
    "name": "YouBeli",
    "url": "http://www.youbeli.com/",
    "logodesktop": "logo/my/desktop/youbeli.png",
    "traffics": 189400,
    "ios": 16,
    "android": 15,
    "twitter": 350,
    "instagram": 2010,
    "facebook": 66900,
    "employees": 6,
    "type": "b2c",
    "category": "general",
    "location": "malaysia",
    "verified": "",
    "iema_winner": ""
  },
  {
    "key": 17,
    "name": "Mysale",
    "url": "https://www.mysale.my",
    "logodesktop": "logo/my/desktop/mysale.png",
    "traffics": 178600,
    "ios": 99,
    "android": 99,
    "twitter": 910,
    "instagram": 2960,
    "facebook": 1238000,
    "employees": 28,
    "type": "b2c",
    "category": "general",
    "location": "international",
    "verified": "",
    "iema_winner": ""
  },
  {
    "key": 18,
    "name": "Poplook",
    "url": "http://poplook.com/",
    "logodesktop": "logo/my/desktop/poplook.png",
    "traffics": 156700,
    "ios": 12,
    "android": 14,
    "twitter": 10050,
    "instagram": 526240,
    "facebook": 328400,
    "employees": 23,
    "type": "b2c",
    "category": "fashion",
    "location": "malaysia",
    "verified": "",
    "iema_winner": ""
  },
  {
    "key": 19,
    "name": "Nile",
    "url": "http://www.nile.com.my/",
    "logodesktop": "logo/my/desktop/nile.png",
    "traffics": 137400,
    "ios": 99,
    "android": 99,
    "twitter": 1410,
    "instagram": 47260,
    "facebook": 483500,
    "employees": 5,
    "type": "b2c",
    "category": "general",
    "location": "malaysia",
    "verified": "",
    "iema_winner": ""
  },
  {
    "key": 20,
    "name": "Althea",
    "url": "http://my.althea.kr/",
    "logodesktop": "logo/my/desktop/althea.png",
    "traffics": 131800,
    "ios": 14,
    "android": 13,
    "twitter": 1230,
    "instagram": 183160,
    "facebook": 554700,
    "employees": 17,
    "type": "b2c",
    "category": "fashion",
    "location": "international",
    "verified": "",
    "iema_winner": ""
  },
  {
    "key": 21,
    "name": "Motherhood",
    "url": "http://www.motherhood.com.my/",
    "logodesktop": "logo/my/desktop/motherhood.png",
    "traffics": 122100,
    "ios": 99,
    "android": 99,
    "twitter": 170,
    "instagram": 56680,
    "facebook": 204100,
    "employees": 20,
    "type": "b2c",
    "category": "fashion",
    "location": "malaysia",
    "verified": "",
    "iema_winner": ""
  },
  {
    "key": 22,
    "name": "Printcious",
    "url": "http://printcious.com",
    "logodesktop": "logo/my/desktop/Printcious.png",
    "traffics": 114900,
    "ios": 99,
    "android": 99,
    "twitter": 40,
    "instagram": 4170,
    "facebook": 73900,
    "employees": 30,
    "type": "b2c",
    "category": "general",
    "location": "malaysia",
    "verified": "TRUE",
    "iema_winner": ""
  },
  {
    "key": 23,
    "name": "Gundam",
    "url": "www.gundam.my",
    "logodesktop": "logo/my/desktop/gundam.png",
    "traffics": 108100,
    "ios": 99,
    "android": 99,
    "twitter": 270,
    "instagram": 16870,
    "facebook": 113700,
    "employees": 1,
    "type": "b2c",
    "category": "general",
    "location": "malaysia",
    "verified": "",
    "iema_winner": ""
  },
  {
    "key": 24,
    "name": "Siti Khadijah",
    "url": "https://sitikhadijah.com/",
    "logodesktop": "logo/my/desktop/sitikhadijah.png",
    "traffics": 106400,
    "ios": 99,
    "android": 99,
    "twitter": 0,
    "instagram": 139070,
    "facebook": 467700,
    "employees": 12,
    "type": "b2c",
    "category": "fashion",
    "location": "malaysia",
    "verified": "",
    "iema_winner": ""
  },
  {
    "key": 25,
    "name": "The One Mall",
    "url": "http://theonemall.com/",
    "logodesktop": "logo/my/desktop/theonemall.png",
    "traffics": 106400,
    "ios": 99,
    "android": 99,
    "twitter": 0,
    "instagram": 68950,
    "facebook": 881000,
    "employees": 1,
    "type": "b2c",
    "category": "general",
    "location": "international",
    "verified": "",
    "iema_winner": ""
  },
  {
    "key": 26,
    "name": "Mis Claire",
    "url": "http://www.misclaire.com/",
    "logodesktop": "logo/my/desktop/misclaire.png",
    "traffics": 77400,
    "ios": 99,
    "android": 99,
    "twitter": 70,
    "instagram": 72480,
    "facebook": 221400,
    "employees": 1,
    "type": "b2c",
    "category": "fashion",
    "location": "malaysia",
    "verified": "",
    "iema_winner": ""
  },
  {
    "key": 27,
    "name": "Superbuy",
    "url": "http://www.superbuy.my/",
    "logodesktop": "logo/my/desktop/superbuy.png",
    "traffics": 70500,
    "ios": 99,
    "android": 99,
    "twitter": 510,
    "instagram": 1060,
    "facebook": 29500,
    "employees": 3,
    "type": "b2c",
    "category": "general",
    "location": "malaysia",
    "verified": "",
    "iema_winner": ""
  },
  {
    "key": 28,
    "name": "Doublewoot",
    "url": "https://www.double-woot.com/",
    "logodesktop": "logo/my/desktop/doublewoot.png",
    "traffics": 66000,
    "ios": 99,
    "android": 99,
    "twitter": 380,
    "instagram": 119660,
    "facebook": 379100,
    "employees": 1,
    "type": "b2c",
    "category": "fashion",
    "location": "malaysia",
    "verified": "",
    "iema_winner": ""
  },
  {
    "key": 29,
    "name": "Naelofar Hijab",
    "url": "https://naelofarhijab.com/",
    "logodesktop": "logo/my/desktop/naelofarhijab.png",
    "traffics": 59200,
    "ios": 99,
    "android": 99,
    "twitter": 120,
    "instagram": 617150,
    "facebook": 12000,
    "employees": 26,
    "type": "b2c",
    "category": "fashion",
    "location": "malaysia",
    "verified": "",
    "iema_winner": ""
  },
  {
    "key": 30,
    "name": "Aidijuma",
    "url": "http://aidijuma.com/",
    "logodesktop": "logo/my/desktop/aidijuma.png",
    "traffics": 55700,
    "ios": 17,
    "android": 17,
    "twitter": 190,
    "instagram": 515710,
    "facebook": 1054900,
    "employees": 13,
    "type": "b2c",
    "category": "fashion",
    "location": "malaysia",
    "verified": "",
    "iema_winner": ""
  },
  {
    "key": 31,
    "name": "Bodying",
    "url": "https://www.bodying.my",
    "logodesktop": "logo/my/desktop/bodying.png",
    "traffics": 55500,
    "ios": 99,
    "android": 99,
    "twitter": 0,
    "instagram": 0,
    "facebook": 120800,
    "employees": 0,
    "type": "b2c",
    "category": "general",
    "location": "international",
    "verified": "",
    "iema_winner": ""
  },
  {
    "key": 32,
    "name": "Babydash",
    "url": "https://www.babydash.com.my/",
    "logodesktop": "logo/my/desktop/babydash.png",
    "traffics": 68200,
    "ios": 99,
    "android": 99,
    "twitter": 270,
    "instagram": 21490,
    "facebook": 133600,
    "employees": 3,
    "type": "b2c",
    "category": "fashion",
    "location": "malaysia",
    "verified": "",
    "iema_winner": ""
  },
  {
    "key": 33,
    "name": "Applecrumby & Fish",
    "url": "https://www.applecrumbyandfish.com/",
    "logodesktop": "logo/my/desktop/applecrumbyfish.png",
    "traffics": 52400,
    "ios": 99,
    "android": 99,
    "twitter": 470,
    "instagram": 13170,
    "facebook": 161600,
    "employees": 16,
    "type": "b2c",
    "category": "fashion",
    "location": "malaysia",
    "verified": "TRUE",
    "iema_winner": ""
  },
  {
    "key": 34,
    "name": "MuslimahClothing.com",
    "url": "https://muslimahclothing.com/",
    "logodesktop": "logo/my/desktop/MuslimahClothing.png",
    "traffics": 52200,
    "ios": 99,
    "android": 99,
    "twitter": 230,
    "instagram": 162910,
    "facebook": 414400,
    "employees": 2,
    "type": "b2c",
    "category": "fashion",
    "location": "malaysia",
    "verified": "",
    "iema_winner": ""
  },
  {
    "key": 35,
    "name": "i-Pmart",
    "url": "http://www.ipmart.com.my",
    "logodesktop": "logo/my/desktop/ipmart.png",
    "traffics": 47000,
    "ios": 99,
    "android": 99,
    "twitter": 600,
    "instagram": 2830,
    "facebook": 800700,
    "employees": 2,
    "type": "b2c",
    "category": "tech",
    "location": "malaysia",
    "verified": "",
    "iema_winner": ""
  },
  {
    "key": 36,
    "name": "Sally Fashion",
    "url": "https://sallyfashion.com.my/",
    "logodesktop": "logo/my/desktop/sallyfashion.png",
    "traffics": 42600,
    "ios": 99,
    "android": 99,
    "twitter": 0,
    "instagram": 6900,
    "facebook": 830600,
    "employees": 1,
    "type": "b2c",
    "category": "fashion",
    "location": "malaysia",
    "verified": "",
    "iema_winner": ""
  },
  {
    "key": 37,
    "name": "Wedding.com.my",
    "url": "http://www.wedding.com.my/",
    "logodesktop": "logo/my/desktop/wedding.png",
    "traffics": 35500,
    "ios": 99,
    "android": 99,
    "twitter": 730,
    "instagram": 26750,
    "facebook": 150900,
    "employees": 20,
    "type": "b2c",
    "category": "fashion",
    "location": "malaysia",
    "verified": "",
    "iema_winner": ""
  },
  {
    "key": 38,
    "name": "Cristy Ng",
    "url": "http://www.christyng.com/",
    "logodesktop": "logo/my/desktop/cristyng.png",
    "traffics": 34500,
    "ios": 99,
    "android": 99,
    "twitter": 1890,
    "instagram": 209430,
    "facebook": 436300,
    "employees": 8,
    "type": "b2c",
    "category": "fashion",
    "location": "malaysia",
    "verified": "",
    "iema_winner": ""
  },
  {
    "key": 39,
    "name": "Calaqisya",
    "url": "http://calaqisya.com/",
    "logodesktop": "logo/my/desktop/calaqisya.png",
    "traffics": 31700,
    "ios": 99,
    "android": 99,
    "twitter": 8150,
    "instagram": 552700,
    "facebook": 237100,
    "employees": 11,
    "type": "b2c",
    "category": "fashion",
    "location": "malaysia",
    "verified": "",
    "iema_winner": ""
  },
  {
    "key": 40,
    "name": "Summerglitz",
    "url": "http://summerglitz.com.my/",
    "logodesktop": "logo/my/desktop/summerglitz.png",
    "traffics": 28700,
    "ios": 99,
    "android": 99,
    "twitter": 0,
    "instagram": 0,
    "facebook": 646000,
    "employees": 0,
    "type": "b2c",
    "category": "fashion",
    "location": "malaysia",
    "verified": "",
    "iema_winner": ""
  },
  {
    "key": 41,
    "name": "Bella Ammara",
    "url": "https://www.bellaammara.com/",
    "logodesktop": "logo/my/desktop/bellaammara.png",
    "traffics": 28600,
    "ios": 99,
    "android": 99,
    "twitter": 1150,
    "instagram": 873320,
    "facebook": 1000,
    "employees": 5,
    "type": "b2c",
    "category": "fashion",
    "location": "malaysia",
    "verified": "",
    "iema_winner": ""
  },
  {
    "key": 42,
    "name": "Curves",
    "url": "http://www.curveskk.com/",
    "logodesktop": "logo/my/desktop/Curves.png",
    "traffics": 26500,
    "ios": 99,
    "android": 99,
    "twitter": 0,
    "instagram": 18640,
    "facebook": 475500,
    "employees": 0,
    "type": "b2c",
    "category": "fashion",
    "location": "malaysia",
    "verified": "",
    "iema_winner": ""
  },
  {
    "key": 43,
    "name": "QQ Baby Shop",
    "url": "http://qqbabyshop.com/",
    "logodesktop": "logo/my/desktop/qqbabyshop.png",
    "traffics": 24200,
    "ios": 99,
    "android": 99,
    "twitter": 0,
    "instagram": 990,
    "facebook": 1019800,
    "employees": 0,
    "type": "b2c",
    "category": "fashion",
    "location": "malaysia",
    "verified": "",
    "iema_winner": ""
  },
  {
    "key": 44,
    "name": "JelitaSara",
    "url": "http://www.jelitasara.com/onlineshop/",
    "logodesktop": "logo/my/desktop/jelitasara.png",
    "traffics": 20800,
    "ios": 99,
    "android": 99,
    "twitter": 430,
    "instagram": 171430,
    "facebook": 342100,
    "employees": 2,
    "type": "b2c",
    "category": "fashion",
    "location": "malaysia",
    "verified": "",
    "iema_winner": ""
  },
  {
    "key": 45,
    "name": "Rina Salleh",
    "url": "http://www.rinasalleh.com/",
    "logodesktop": "logo/my/desktop/RinaSalleh.png",
    "traffics": 20800,
    "ios": 99,
    "android": 99,
    "twitter": 0,
    "instagram": 52200,
    "facebook": 162600,
    "employees": 2,
    "type": "b2c",
    "category": "fashion",
    "location": "malaysia",
    "verified": "",
    "iema_winner": ""
  },
  {
    "key": 46,
    "name": "La Rossa",
    "url": "http://larossa.com.my/",
    "logodesktop": "logo/my/desktop/larossa.png",
    "traffics": 20600,
    "ios": 99,
    "android": 99,
    "twitter": 0,
    "instagram": 0,
    "facebook": 211900,
    "employees": 0,
    "type": "b2c",
    "category": "fashion",
    "location": "malaysia",
    "verified": "",
    "iema_winner": ""
  },
  {
    "key": 47,
    "name": "Twenty3",
    "url": "https://www.twenty3.my/",
    "logodesktop": "logo/my/desktop/twenty3.png",
    "traffics": 19800,
    "ios": 99,
    "android": 99,
    "twitter": 0,
    "instagram": 85840,
    "facebook": 392900,
    "employees": 1,
    "type": "b2c",
    "category": "fashion",
    "location": "malaysia",
    "verified": "",
    "iema_winner": ""
  },
  {
    "key": 48,
    "name": "Radiusite",
    "url": "http://radiusite.com.my/",
    "logodesktop": "logo/my/desktop/radiusite.png",
    "traffics": 17000,
    "ios": 99,
    "android": 99,
    "twitter": 20,
    "instagram": 435390,
    "facebook": 702900,
    "employees": 5,
    "type": "b2c",
    "category": "fashion",
    "location": "malaysia",
    "verified": "",
    "iema_winner": ""
  },
  {
    "key": 49,
    "name": "Qaira Hijab",
    "url": "http://www.qairahijab.com.my/",
    "logodesktop": "logo/my/desktop/qairahijab.png",
    "traffics": 13200,
    "ios": 99,
    "android": 99,
    "twitter": 0,
    "instagram": 163000,
    "facebook": 568700,
    "employees": 1,
    "type": "b2c",
    "category": "fashion",
    "location": "malaysia",
    "verified": "",
    "iema_winner": ""
  }
]
}